{"nodes": [{"id": "serverng_internal_codec_compress_fft_go", "label": "compress_fft.go", "file_type": "code", "source_file": "serverng/internal/codec/compress_fft.go", "source_location": "L1"}, {"id": "codec_compress_fft_compressfft", "label": "CompressFft()", "file_type": "code", "source_file": "serverng/internal/codec/compress_fft.go", "source_location": "L6"}, {"id": "codec_compress_fft_compressfftinto", "label": "compressFftInto()", "file_type": "code", "source_file": "serverng/internal/codec/compress_fft.go", "source_location": "L13"}, {"id": "codec_compress_fft_deltaencode", "label": "DeltaEncode()", "file_type": "code", "source_file": "serverng/internal/codec/compress_fft.go", "source_location": "L39"}, {"id": "codec_compress_fft_deltadecode", "label": "DeltaDecode()", "file_type": "code", "source_file": "serverng/internal/codec/compress_fft.go", "source_location": "L53"}], "edges": [{"source": "serverng_internal_codec_compress_fft_go", "target": "codec_compress_fft_compressfft", "relation": "contains", "confidence": "EXTRACTED", "source_file": "serverng/internal/codec/compress_fft.go", "source_location": "L6", "weight": 1.0}, {"source": "serverng_internal_codec_compress_fft_go", "target": "codec_compress_fft_compressfftinto", "relation": "contains", "confidence": "EXTRACTED", "source_file": "serverng/internal/codec/compress_fft.go", "source_location": "L13", "weight": 1.0}, {"source": "serverng_internal_codec_compress_fft_go", "target": "codec_compress_fft_deltaencode", "relation": "contains", "confidence": "EXTRACTED", "source_file": "serverng/internal/codec/compress_fft.go", "source_location": "L39", "weight": 1.0}, {"source": "serverng_internal_codec_compress_fft_go", "target": "codec_compress_fft_deltadecode", "relation": "contains", "confidence": "EXTRACTED", "source_file": "serverng/internal/codec/compress_fft.go", "source_location": "L53", "weight": 1.0}, {"source": "codec_compress_fft_compressfft", "target": "codec_compress_fft_compressfftinto", "relation": "calls", "confidence": "EXTRACTED", "source_file": "serverng/internal/codec/compress_fft.go", "source_location": "L8", "weight": 1.0}], "raw_calls": [{"caller_nid": "codec_compress_fft_compressfft", "callee": "make", "is_member_call": false, "source_file": "serverng/internal/codec/compress_fft.go", "source_location": "L7"}, {"caller_nid": "codec_compress_fft_compressfft", "callee": "len", "is_member_call": false, "source_file": "serverng/internal/codec/compress_fft.go", "source_location": "L7"}, {"caller_nid": "codec_compress_fft_compressfftinto", "callee": "float32", "is_member_call": false, "source_file": "serverng/internal/codec/compress_fft.go", "source_location": "L23"}, {"caller_nid": "codec_compress_fft_compressfftinto", "callee": "byte", "is_member_call": false, "source_file": "serverng/internal/codec/compress_fft.go", "source_location": "L31"}, {"caller_nid": "codec_compress_fft_deltaencode", "callee": "len", "is_member_call": false, "source_file": "serverng/internal/codec/compress_fft.go", "source_location": "L40"}, {"caller_nid": "codec_compress_fft_deltaencode", "callee": "make", "is_member_call": false, "source_file": "serverng/internal/codec/compress_fft.go", "source_location": "L43"}, {"caller_nid": "codec_compress_fft_deltaencode", "callee": "len", "is_member_call": false, "source_file": "serverng/internal/codec/compress_fft.go", "source_location": "L43"}, {"caller_nid": "codec_compress_fft_deltaencode", "callee": "len", "is_member_call": false, "source_file": "serverng/internal/codec/compress_fft.go", "source_location": "L45"}, {"caller_nid": "codec_compress_fft_deltadecode", "callee": "len", "is_member_call": false, "source_file": "serverng/internal/codec/compress_fft.go", "source_location": "L54"}, {"caller_nid": "codec_compress_fft_deltadecode", "callee": "make", "is_member_call": false, "source_file": "serverng/internal/codec/compress_fft.go", "source_location": "L57"}, {"caller_nid": "codec_compress_fft_deltadecode", "callee": "len", "is_member_call": false, "source_file": "serverng/internal/codec/compress_fft.go", "source_location": "L57"}, {"caller_nid": "codec_compress_fft_deltadecode", "callee": "len", "is_member_call": false, "source_file": "serverng/internal/codec/compress_fft.go", "source_location": "L59"}]}